setup.py
test_pypi_nathanwilk7/__init__.py
test_pypi_nathanwilk7/test_pypi_file.py
test_pypi_nathanwilk7.egg-info/PKG-INFO
test_pypi_nathanwilk7.egg-info/SOURCES.txt
test_pypi_nathanwilk7.egg-info/dependency_links.txt
test_pypi_nathanwilk7.egg-info/top_level.txt