Metadata-Version: 1.0
Name: test-pypi-nathanwilk7
Version: 0.3.0
Summary: Test for conda recursion channel
Home-page: UNKNOWN
Author: Recursion Pharmaceuticals
Author-email: dev@recursionpharma.com
License: UNKNOWN
Platform: UNKNOWN
